setup.py
fmaya/__init__.py
fmaya/base.py
fmaya.egg-info/PKG-INFO
fmaya.egg-info/SOURCES.txt
fmaya.egg-info/dependency_links.txt
fmaya.egg-info/not-zip-safe
fmaya.egg-info/top_level.txt