Metadata-Version: 1.0
Name: fmaya
Version: 0.1
Summary: Functional expressions for Autodesk Maya.
Home-page: https://github.com/gfixler/fmaya
Author: Gary Fixler
Author-email: gfixler@gmail.com
License: GNU GPLv3
Platform: UNKNOWN
